LICENSE
MANIFEST.in
Makefile
README.rst
requirements.txt
setup.py
examples/clien.py
examples/config.yaml.sample
test/__init__.py
test/helpers.py
test/test_app.py
test/test_utils.py
test/interactive/cgv.py
test/interactive/clien.py
test/notifications/__init__.py
test/notifications/test_email.py
test/sites/__init__.py
test/sites/cgv/__init__.py
test/sites/cgv/date_list_77200_20004051_0074.html
test/sites/cgv/format_list_77200.html
test/sites/cgv/home_logged_in.html
test/sites/cgv/home_not_logged_in.html
test/sites/cgv/login_failed.html
test/sites/cgv/login_required.html
test/sites/cgv/movie_list.html
test/sites/cgv/pages.yaml
test/sites/cgv/seat_list_0074_20131108_009_1.html
test/sites/cgv/seat_list_0074_20131109_009_6.html
test/sites/cgv/test_cgv.py
test/sites/cgv/theater_list_77200_20004051.html
test/sites/cgv/time_list_77200_20004051_0074_20131108.html
test/sites/cgv/time_list_77200_20004051_0074_20131113.html
test/sites/clien/__init__.py
test/sites/clien/board_chehum_page_56.html
test/sites/clien/board_lecture_page_2.html
test/sites/clien/board_news_page_3.html
test/sites/clien/board_sold_page_1.html
test/sites/clien/home_logged_in.html
test/sites/clien/home_not_logged_in.html
test/sites/clien/login_required.html
test/sites/clien/pages.yaml
test/sites/clien/post_cm_mac_id_727448.html
test/sites/clien/post_deleted.html
test/sites/clien/post_invalid_markup.html
test/sites/clien/post_kin_id_2953977.html
test/sites/clien/post_news_id_1713648.html
test/sites/clien/post_sold_id_701508.html
test/sites/clien/post_sold_id_705985.html
test/sites/clien/test_clien.py
webalerts/__init__.py
webalerts/app.py
webalerts/exceptions.py
webalerts/utils.py
webalerts/version.py
webalerts.egg-info/PKG-INFO
webalerts.egg-info/SOURCES.txt
webalerts.egg-info/dependency_links.txt
webalerts.egg-info/requires.txt
webalerts.egg-info/top_level.txt
webalerts/notifications/__init__.py
webalerts/notifications/console.py
webalerts/notifications/email.py
webalerts/sites/__init__.py
webalerts/sites/cgv.py
webalerts/sites/clien.py
webalerts/sites/navercafe.py