Metadata-Version: 1.1
Name: webalerts
Version: 0.0.3
Summary: WebAlerts is a Python package that lets you be notified for new website posts matching your regex patterns.
Home-page: https://github.com/clee704/WebAlerts
Author: Choongmin Lee
Author-email: choongmin@me.com
License: MIT License
Keywords: web crawler notification
Platform: UNKNOWN
Classifier: Development Status :: 2 - Pre-Alpha
Classifier: Intended Audience :: Developers
Classifier: Intended Audience :: End Users/Desktop
Classifier: License :: OSI Approved :: MIT License
Classifier: Programming Language :: Python
Classifier: Topic :: Internet
